kosmos/__init__.py
kosmos/circuit_runner/__init__.py
kosmos/circuit_runner/circuit_runner.py
kosmos/circuit_runner/ibm_runtime_utils.py
kosmos/circuit_runner/pennylane_runner.py
kosmos/circuit_runner/qiskit_result.py
kosmos/circuit_runner/qiskit_runner.py
kosmos/circuit_runner/typing.py
kosmos/ml/__init__.py
kosmos/ml/cl_manager.py
kosmos/ml/dataloader.py
kosmos/ml/sl_metrics.py
kosmos/ml/sl_result.py
kosmos/ml/sl_trainer.py
kosmos/ml/typing.py
kosmos/ml/config/__init__.py
kosmos/ml/config/sl_train.py
kosmos/ml/config/factories/__init__.py
kosmos/ml/config/factories/encoding.py
kosmos/ml/config/factories/loss.py
kosmos/ml/config/factories/lr_scheduler.py
kosmos/ml/config/factories/model.py
kosmos/ml/config/factories/optimizer.py
kosmos/ml/datasets/__init__.py
kosmos/ml/datasets/banknote_dataset.py
kosmos/ml/datasets/bloodmnist_dataset.py
kosmos/ml/datasets/dataset.py
kosmos/ml/datasets/digits_dataset.py
kosmos/ml/datasets/income_dataset.py
kosmos/ml/datasets/iris_dataset.py
kosmos/ml/datasets/mnist_dataset.py
kosmos/ml/datasets/organamnist_dataset.py
kosmos/ml/datasets/qsar_dataset.py
kosmos/ml/datasets/wdbc_dataset.py
kosmos/ml/datasets/wine_dataset.py
kosmos/ml/datasets/data/__init__.py
kosmos/ml/datasets/data/adult.data
kosmos/ml/datasets/data/banknote.data
kosmos/ml/datasets/data/bloodmnist.npz
kosmos/ml/datasets/data/iris.data
kosmos/ml/datasets/data/mnist.data.gz
kosmos/ml/datasets/data/organamnist.npz
kosmos/ml/datasets/data/qsar.data
kosmos/ml/datasets/data/wdbc.data
kosmos/ml/fl/__init__.py
kosmos/ml/fl/fl_client.py
kosmos/ml/fl/fl_manager.py
kosmos/ml/fl/fl_server.py
kosmos/ml/models/__init__.py
kosmos/ml/models/model.py
kosmos/ml/models/neural_network.py
kosmos/ml/models/vqc/__init__.py
kosmos/ml/models/vqc/vqc.py
kosmos/ml/models/vqc/circuit/__init__.py
kosmos/ml/models/vqc/circuit/circuit.py
kosmos/ml/models/vqc/circuit/pennylane_circuit.py
kosmos/ml/models/vqc/circuit/qiskit_circuit/__init__.py
kosmos_core-0.5.2.dist-info/licenses/LICENSE
kosmos_core-0.5.2.dist-info/METADATA
kosmos_core-0.5.2.dist-info/WHEEL
kosmos_core-0.5.2.dist-info/top_level.txt
kosmos_core-0.5.2.dist-info/RECORD
