Metadata-Version: 2.4
Name: kosmos-core
Version: 0.5.2
Summary: Koordinations-, Optimierungs- und Simulations-Software für Modulare Quanten-Systeme in 6G Netzwerken
Author-email: Michael Kölle <michael.koelle@aignosco.com>
License-Expression: MIT
Keywords: api,kosmos,kosmos-core
Classifier: Development Status :: 3 - Alpha
Classifier: Intended Audience :: Developers
Classifier: Programming Language :: Python :: 3
Classifier: Programming Language :: Python :: 3.13
Requires-Python: >=3.13
License-File: LICENSE
Requires-Dist: pydantic>=2.12.4
Requires-Dist: pydantic-settings>=2.12.0
Requires-Dist: numpy>=2.3.5
Requires-Dist: torch>=2.9.1
Requires-Dist: scikit-learn>=1.7.2
Requires-Dist: pandas>=2.3.3
Requires-Dist: scipy>=1.16.3
Requires-Dist: pennylane>=0.43.1
Requires-Dist: pennylane-lightning>=0.43.0
Requires-Dist: qiskit>=2.2.3
Requires-Dist: qiskit-aer>=0.17.2
Requires-Dist: qiskit-ibm-runtime==0.41.1
Requires-Dist: pymetis>=2025.2.2; sys_platform != "win32"
Provides-Extra: dev
Requires-Dist: pytest>=9.0.1; extra == "dev"
Requires-Dist: pytest-cov>=7.0.0; extra == "dev"
Requires-Dist: pytest-asyncio>=1.3.0; extra == "dev"
Requires-Dist: ruff>=0.14.5; extra == "dev"
Requires-Dist: pre-commit>=4.4.0; extra == "dev"
Requires-Dist: pipreqs>=0.4.13; extra == "dev"
Requires-Dist: sphinx>=8.2.3; extra == "dev"
Requires-Dist: sphinx-autoapi>=3.6.1; extra == "dev"
Requires-Dist: sphinx-copybutton>=0.5.2; extra == "dev"
Requires-Dist: furo>=2025.9.25; extra == "dev"
Dynamic: license-file
